private_set_intersection/proto/psi_python_proto_pb/private_set_intersection/proto/psi_pb2.py
private_set_intersection/python/__init__.py
private_set_intersection/python/_openmined_psi.so
site-packages/__init__.py
site-packages/google/__init__.py
site-packages/google/_upb/__init__.py
site-packages/google/_upb/_message.abi3.so
site-packages/google/protobuf/__init__.py
site-packages/google/protobuf/any_pb2.py
site-packages/google/protobuf/api_pb2.py
site-packages/google/protobuf/compiler/__init__.py
site-packages/google/protobuf/compiler/plugin_pb2.py
site-packages/google/protobuf/descriptor.py
site-packages/google/protobuf/descriptor_database.py
site-packages/google/protobuf/descriptor_pb2.py
site-packages/google/protobuf/descriptor_pool.py
site-packages/google/protobuf/duration_pb2.py
site-packages/google/protobuf/empty_pb2.py
site-packages/google/protobuf/field_mask_pb2.py
site-packages/google/protobuf/internal/__init__.py
site-packages/google/protobuf/internal/_parameterized.py
site-packages/google/protobuf/internal/api_implementation.py
site-packages/google/protobuf/internal/builder.py
site-packages/google/protobuf/internal/containers.py
site-packages/google/protobuf/internal/decoder.py
site-packages/google/protobuf/internal/encoder.py
site-packages/google/protobuf/internal/enum_type_wrapper.py
site-packages/google/protobuf/internal/extension_dict.py
site-packages/google/protobuf/internal/field_mask.py
site-packages/google/protobuf/internal/message_listener.py
site-packages/google/protobuf/internal/python_edition_defaults.py
site-packages/google/protobuf/internal/python_message.py
site-packages/google/protobuf/internal/testing_refleaks.py
site-packages/google/protobuf/internal/type_checkers.py
site-packages/google/protobuf/internal/well_known_types.py
site-packages/google/protobuf/internal/wire_format.py
site-packages/google/protobuf/json_format.py
site-packages/google/protobuf/message.py
site-packages/google/protobuf/message_factory.py
site-packages/protobuf-5.27.2.dist-info/INSTALLER
site-packages/protobuf-5.27.2.dist-info/LICENSE
site-packages/protobuf-5.27.2.dist-info/METADATA
site-packages/protobuf-5.27.2.dist-info/WHEEL
openmined_psi-2.0.5.dist-info/WHEEL
openmined_psi-2.0.5.dist-info/METADATA
openmined_psi-2.0.5.dist-info/LICENSE
openmined_psi-2.0.5.dist-info/README
openmined_psi-2.0.5.dist-info/RECORD
