Metadata-Version: 2.1
Name: openmined_psi
Author: OpenMined
Home-page: https://github.com/OpenMined/PSI
License: Apache 2.0
Classifier: Programming Language :: Python :: 3
Classifier: Operating System :: OS Independent
Classifier: Topic :: Security :: Cryptography
Requires-Python: >=3.8
Requires-Dist: protobuf==5.27.2
Version: 2.0.5
